week 7/ripple_tb.v
// Sequence: 00 → 01 → 10 → 11 → 00 → …
`timescale 1ns/1ps
module dff (
input wire clk,
input wire rst, // async reset, active-high
input wire d,
output reg q
);
always @(posedge clk or posedge rst) begin
if (rst) q <= 1'b0;
else q <= d;
end
endmodule

module ripple_up_counter_2bit (
input wire clk,
input wire rst,
output wire [1:0] q
);
wire q0, q1;
// LSB toggles every system clock
dff ff0 (.clk(clk), .rst(rst), .d(~q0), .q(q0));
// MSB toggles when q0 falls (use posedge of ~q0)
dff ff1 (.clk(~q0), .rst(rst), .d(~q1), .q(q1));
assign q = {q1, q0};
endmodule

module tb_ripple_counter;
reg clk, rst;
wire [1:0] q;

ripple_up_counter_2bit uut (.clk(clk), .rst(rst), .q(q));

initial begin
clk = 0;
forever #5 clk = ~clk;
end

initial begin
$dumpfile("ripple_counter.vcd");
$dumpvars(0, tb_ripple_counter);
$display("Time\tClk\tReset\tQ1Q0");
$monitor("%0t\t%b\t%b\t%b%b", $time, clk, rst, q[1], q[0]);
rst = 1; #10;
rst = 0; #80;
rst = 1; #10;
rst = 0; #40;
$finish;
end
endmodule

week 7/ripple_counter.vcd
$date
	Mon Sep 29 15:12:51 2025
$end
$version
	Icarus Verilog
$end
$timescale
	1ps
$end
$scope module tb_ripple_counter $end
$var wire 2 ! q [1:0] $end
$var reg 1 " clk $end
$var reg 1 # rst $end
$scope module uut $end
$var wire 1 $ clk $end
$var wire 2 % q [1:0] $end
$var wire 1 & q0 $end
$var wire 1 ' q1 $end
$var wire 1 ( rst $end
$scope module ff0 $end
$var wire 1 $ clk $end
$var wire 1 ) d $end
$var wire 1 ( rst $end
$var reg 1 * q $end
$upscope $end
$scope module ff1 $end
$var wire 1 + clk $end
$var wire 1 , d $end
$var wire 1 ( rst $end
$var reg 1 - q $end
$upscope $end
$upscope $end
$upscope $end
$enddefinitions $end
#0
$dumpvars
0-
1,
1+
0*
1)
1(
0'
0&
b0 %
0$
1#
0"
b0 !
$end
#5000
1"
1$
#10000
0"
0$
0#
0(
#15000
0+
0)
1*
b1 !
b1 %
1&
1"
1$
#20000
0"
0$
#25000
0,
1-
1'
1+
1)
0*
b10 !
b10 %
0&
1"
1$
#30000
0"
0$
#35000
0+
0)
1*
b11 !
b11 %
1&
1"
1$
#40000
0"
0$
#45000
1,
0-
0'
1+
1)
0*
b0 !
b0 %
0&
1"
1$
#50000
0"
0$
#55000
0+
0)
1*
b1 !
b1 %
1&
1"
1$
#60000
0"
0$
#65000
0,
1-
1'
1+
1)
0*
b10 !
b10 %
0&
1"
1$
#70000
0"
0$
#75000
0+
0)
1*
b11 !
b11 %
1&
1"
1$
#80000
0"
0$
#85000
1,
0-
0'
1+
1)
0*
b0 !
b0 %
0&
1"
1$
#90000
0"
0$
1#
1(
#95000
1"
1$
#100000
0"
0$
0#
0(
#105000
0+
0)
1*
b1 !
b1 %
1&
1"
1$
#110000
0"
0$
#115000
0,
1-
1'
1+
1)
0*
b10 !
b10 %
0&
1"
1$
#120000
0"
0$
#125000
0+
0)
1*
b11 !
b11 %
1&
1"
1$
#130000
0"
0$
#135000
1,
0-
0'
1+
1)
0*
b0 !
b0 %
0&
1"
1$
