week 6/tflipflop/tflipflop.v
module t_ff (input wire T, input wire clk, input wire rst, output reg Q);

always @(posedge clk )
	 begin  if (rst) 
                   Q <= 1'b0;  
                 else if (T)    Q <= ~Q;   // toggle  
	else    Q <= Q;    // hold
end
endmodule

week 6/tflipflop/tflipflop_tb.v
module TB_T; 
 reg T;  
reg CLK;
  reg RST;  
wire Q; 
 // Instantiate T flip-flop 
 t_ff newT (.T(T), .clk(CLK), .rst(RST), .Q(Q));
  // Clock generation: 10 time units period
  initial begin
    CLK = 1'b0;
    forever #5 CLK = ~CLK;
  end
// Waveform dump 
 initial 
begin   
 $dumpfile("t_ff.vcd");   
 $dumpvars(0, TB_T);  
end 
 // Monitor prints automatically whenever any signal changes  
initial 
begin   
 $monitor("Time=%0t | RST=%b | T=%b | Q=%b", $time, RST, T, Q);
  end
 // Stimulus
  initial
 begin
   RST = 1'b1;
 T = 1'b0; #7;
    RST = 1'b0; #8; 
   T = 1'b0; #20;  // hold
    T = 1'b1; #40;  // toggle
    T = 1'b0; #20;  // hold  
  RST = 1'b1; #6;  
  RST = 1'b0; #14;    
$finish;
end

endmodule

week 6/tflipflop/t_ff.vcd
$date
	Mon Sep 08 14:46:28 2025
$end
$version
	Icarus Verilog
$end
$timescale
	1s
$end
$scope module TB_T $end
$var wire 1 ! Q $end
$var reg 1 " CLK $end
$var reg 1 # RST $end
$var reg 1 $ T $end
$scope module newT $end
$var wire 1 % T $end
$var wire 1 & clk $end
$var wire 1 ' rst $end
$var reg 1 ( Q $end
$upscope $end
$upscope $end
$enddefinitions $end
#0
$dumpvars
x(
1'
0&
0%
0$
1#
0"
x!
$end
#5
0(
0!
1"
1&
#7
0#
0'
#10
0"
0&
#15
1"
1&
#20
0"
0&
#25
1"
1&
#30
0"
0&
#35
1(
1!
1"
1&
1$
1%
#40
0"
0&
#45
0(
0!
1"
1&
#50
0"
0&
#55
1(
1!
1"
1&
#60
0"
0&
#65
0(
0!
1"
1&
#70
0"
0&
#75
1"
1&
0$
0%
#80
0"
0&
#85
1"
1&
#90
0"
0&
#95
1"
1&
1#
1'
#100
0"
0&
#101
0#
0'
