week 3/basic/basic.v
module and2(a, b, c);
    input a, b;
    output c;
    assign c = a & b;
endmodule

module or2(a, b, c);
    input a, b;
    output c;
    assign c = a | b;
endmodule

module xor2(a, b, c);
    input a, b;
    output c;
    assign c = a ^ b;
endmodule

module not1(a, c);
    input a;
    output c;
    assign c = ~a;
endmodule

week 3/fulladder/fulladder.v
module fulladder(a, b, cin, sum, cout);
    input a, b, cin;
    output sum, cout;
    wire w1, w2, w3, w4, w5;

    xor2 x1(a, b, w1);
    xor2 x2(w1, cin, sum);

    and2 a1(a, b, w2);
    and2 a2(b, cin, w3);
    and2 a3(a, cin, w4);
    or2 o1(w2, w3, w5);
    or2 o2(w5, w4, cout);
endmodule

week 3/fulladder/fulladder_tb.v
module fulladder_tb;
	reg aa, bb, cc;
	wire ss, cy;

	fulladder uut(.a(aa),.b(bb),.cin(cc),.sum(ss),.cout(cy));

	initial begin
		$dumpfile("fulladder_test.vcd");
		$dumpvars(0, fulladder_tb);
	end

	initial begin
		$monitor($time, "a=%b, b=%b, cin=%b, sum=%b, cout=%b", aa, bb, cc, ss, cy);
		#5 aa=1'b0; bb=1'b0; cc=1'b0;
		#5 aa=1'b0; bb=1'b1; cc=1'b0;
		#5 aa=1'b1; bb=1'b0; cc=1'b0;
		#5 aa=1'b1; bb=1'b1; cc=1'b0;
		#5 aa=1'b0; bb=1'b0; cc=1'b1;
		#5 aa=1'b0; bb=1'b1; cc=1'b1;
		#5 aa=1'b1; bb=1'b0; cc=1'b1;
		#5 aa=1'b1; bb=1'b1; cc=1'b1;
		$finish;
	end
endmodule

week 3/fulladder/fulladder_test.vcd
$date
	Tue Aug 19 20:31:44 2025
$end
$version
	Icarus Verilog
$end
$timescale
	1s
$end
$scope module fulladder_tb $end
$var wire 1 ! cy $end
$var wire 1 " ss $end
$var reg 1 # aa $end
$var reg 1 $ bb $end
$var reg 1 % cc $end
$scope module uut $end
$var wire 1 & a $end
$var wire 1 ' b $end
$var wire 1 ( cin $end
$var wire 1 ! cout $end
$var wire 1 " sum $end
$var wire 1 ) w1 $end
$var wire 1 * w2 $end
$var wire 1 + w3 $end
$var wire 1 , w4 $end
$var wire 1 - w5 $end
$scope module x1 $end
$var wire 1 & a $end
$var wire 1 ' b $end
$var wire 1 ) c $end
$upscope $end
$scope module x2 $end
$var wire 1 ) a $end
$var wire 1 ( b $end
$var wire 1 " c $end
$upscope $end
$scope module a1 $end
$var wire 1 & a $end
$var wire 1 ' b $end
$var wire 1 * c $end
$upscope $end
$scope module a2 $end
$var wire 1 ' a $end
$var wire 1 ( b $end
$var wire 1 + c $end
$upscope $end
$scope module a3 $end
$var wire 1 & a $end
$var wire 1 ( b $end
$var wire 1 , c $end
$upscope $end
$scope module o1 $end
$var wire 1 * a $end
$var wire 1 + b $end
$var wire 1 - c $end
$upscope $end
$scope module o2 $end
$var wire 1 - a $end
$var wire 1 , b $end
$var wire 1 ! c $end
$upscope $end
$upscope $end
$upscope $end
$enddefinitions $end
#0
$dumpvars
x-
x,
x+
x*
x)
x(
x'
x&
x%
x$
x#
x"
x!
$end
#5
0!
0-
0"
0+
0)
0*
0,
0%
0(
0$
0'
0#
0&
#10
1"
1)
1$
1'
#15
0$
0'
1#
1&
#20
1!
0"
1-
0)
1*
1$
1'
#25
0!
0-
1"
0*
1%
1(
0$
0'
0#
0&
#30
1!
0"
1-
1)
1+
1$
1'
#35
0-
0+
1,
0$
0'
1#
1&
#40
1"
1-
0)
1*
1+
1$
1'
