week 4 pdf/mux2/mux2.v
module mux2 (input wire i0, i1, j, output wire o);
assign o = j ? i1 : i0;
endmodule

week 4 pdf/mux4/mux4.v
module mux4 (input wire [3:0] i, input wire j1, j0, output wire o);
wire t0, t1;
mux2 mux2_0 (.i0(i[0]), .i1(i[1]), .j(j0), .o(t0));
mux2 mux2_1 (.i0(i[2]), .i1(i[3]), .j(j0), .o(t1));
mux2 mux2_2 (.i0(t0), .i1(t1), .j(j1), .o(o));
endmodule

week 4 pdf/mux4/mux4_tb.v
module TB;
reg [3:0] ii;
reg s0;
reg s1;
wire yy;
initial begin
	$dumpfile("MUX4_test.vcd");
	$dumpvars(0, TB);
end
mux4 newMUX(.i(ii), .j0(s0), .j1(s1), .o(yy));
initial begin
	ii = 4'b0000; s0 = 1'b0; s1 = 1'b0;
	#5 ii = 4'b1000; s0 = 1'b0; s1 = 1'b0;
	#5 ii = 4'b0000; s0 = 1'b0; s1 = 1'b1;
	#5 ii = 4'b0100; s0 = 1'b0; s1 = 1'b1;
	#5 ii = 4'b0000; s0 = 1'b1; s1 = 1'b0;
	#5 ii = 4'b0010; s0 = 1'b1; s1 = 1'b0;
	#5 ii = 4'b0000; s0 = 1'b1; s1 = 1'b1;
	#5 ii = 4'b0001; s0 = 1'b1; s1 = 1'b1;
end
initial begin
	$monitor("At time %t, s1 = %b, s0 = %b, ii = %b, yy = %b", $time, s1, s0, ii, yy);
end
endmodule

week 4 pdf/mux4/MUX4_test.vcd
$date
	Mon Aug 25 14:52:52 2025
$end
$version
	Icarus Verilog
$end
$timescale
	1s
$end
$scope module TB $end
$var wire 1 ! yy $end
$var reg 4 " ii [3:0] $end
$var reg 1 # s0 $end
$var reg 1 $ s1 $end
$scope module newMUX $end
$var wire 4 % i [3:0] $end
$var wire 1 & j0 $end
$var wire 1 ' j1 $end
$var wire 1 ! o $end
$var wire 1 ( t0 $end
$var wire 1 ) t1 $end
$scope module mux2_0 $end
$var wire 1 * i0 $end
$var wire 1 + i1 $end
$var wire 1 & j $end
$var wire 1 ( o $end
$upscope $end
$scope module mux2_1 $end
$var wire 1 , i0 $end
$var wire 1 - i1 $end
$var wire 1 & j $end
$var wire 1 ) o $end
$upscope $end
$scope module mux2_2 $end
$var wire 1 ( i0 $end
$var wire 1 ) i1 $end
$var wire 1 ' j $end
$var wire 1 ! o $end
$upscope $end
$upscope $end
$upscope $end
$enddefinitions $end
#0
$dumpvars
0-
0,
0+
0*
0)
0(
0'
0&
b0 %
0$
0#
b0 "
0!
$end
#5
1-
b1000 "
b1000 %
#10
0-
1$
1'
b0 "
b0 %
#15
1!
1)
1,
b100 "
b100 %
#20
0!
0)
0,
0$
0'
1#
1&
b0 "
b0 %
#25
1!
1(
1+
b10 "
b10 %
#30
0(
0!
0+
1$
1'
b0 "
b0 %
#35
1*
b1 "
b1 %
