week 6/tflipflop/tflipflop.v
module t_ff (input wire T, input wire clk, input wire rst, output reg Q);

always @(posedge clk )
	 begin  if (rst) 
                   Q <= 1'b0;  
                 else if (T)    Q <= ~Q;   // toggle  
	else    Q <= Q;    // hold
end
endmodule

week 6/d_using_t/d_using_t.v
module d_using_t_ff (input wire D, input wire clk, input wire rst, output wire Q);
wire T_input;
assign T_input = D ^ Q;  // XOR gate logic: T = D XOR Q
t_ff tff1 (.T(T_input), .clk(clk), .rst(rst), .Q(Q));
endmodule

week 6/d_using_t/d_using_t_tb.v
module TB_D_using_T;
reg D;
reg CLK;
reg RST;
wire Q;
d_using_t_ff newD (.D(D), .clk(CLK), .rst(RST), .Q(Q));
initial begin
  CLK=1'b0;
  forever #5 CLK=~CLK;
end
initial begin
  $dumpfile("d_using_t.vcd");
  $dumpvars(0, TB_D_using_T);
end
initial begin
  $monitor("Time=%0t | RST=%b | D=%b | Q=%b", $time, RST, D, Q);
end
initial begin
  RST=1'b1; D=1'b0; #8;
  RST=1'b0; #6;
  D=1'b0; #15;  // Q should follow D
  D=1'b1; #10;  // Q should become 1
  D=1'b0; #10;  // Q should become 0
  D=1'b1; #10;  // Q should become 1
  D=1'b1; #10;  // Q should stay 1
  D=1'b0; #10;  // Q should become 0
  RST=1'b1; #5;
  RST=1'b0; #15;
  $finish;
end
endmodule

week 6/d_using_t/d_using_t.vcd
$date
	Mon Sep 08 14:52:37 2025
$end
$version
	Icarus Verilog
$end
$timescale
	1s
$end
$scope module TB_D_using_T $end
$var wire 1 ! Q $end
$var reg 1 " CLK $end
$var reg 1 # D $end
$var reg 1 $ RST $end
$scope module newD $end
$var wire 1 % D $end
$var wire 1 ! Q $end
$var wire 1 & T_input $end
$var wire 1 ' clk $end
$var wire 1 ( rst $end
$scope module tff1 $end
$var wire 1 & T $end
$var wire 1 ' clk $end
$var wire 1 ( rst $end
$var reg 1 ) Q $end
$upscope $end
$upscope $end
$upscope $end
$enddefinitions $end
#0
$dumpvars
x)
1(
0'
x&
0%
1$
0#
0"
x!
$end
#5
0&
0)
0!
1"
1'
#8
0$
0(
#10
0"
0'
#15
1"
1'
#20
0"
0'
#25
1"
1'
#29
1&
1#
1%
#30
0"
0'
#35
0&
1)
1!
1"
1'
#39
1&
0#
0%
#40
0"
0'
#45
0&
0)
0!
1"
1'
#49
1&
1#
1%
#50
0"
0'
#55
0&
1)
1!
1"
1'
#60
0"
0'
#65
1"
1'
#69
1&
0#
0%
#70
0"
0'
#75
0&
0)
0!
1"
1'
#79
1$
1(
#80
0"
0'
#84
0$
0(
