week 6/jkflipflop/jkflipflop.v
module jk_ff (input wire j, input wire k, input wire clk, input wire rst, output reg q);
always @(posedge clk or posedge rst) 
begin       
 if (rst)            
     q <= 1'b0;                // Reset to 0       
 else begin 
     case ({j, k})             
       2'b00: q <= q;        // No change       
       2'b01: q <= 1'b0;     // Reset       
       2'b10: q <= 1'b1;     // Set            
       2'b11: q <= ~q;       // Toggle          
     endcase       
 end 
end
endmodule

week 6/jkflipflop/jkflipflop_tb.v
`timescale 1ns/1ps
module tb_jk_ff;
  reg j, k, clk, rst;
  wire q;
  jk_ff jk1 (
    .j(j),
    .k(k),
    .clk(clk),
    .rst(rst),
    .q(q)
  );
 initial begin
    clk = 0;
    forever #5 clk = ~clk;
  end
  initial begin
    $dumpfile("jk_ff.vcd");
    $dumpvars(0, tb_jk_ff);
  end
  initial begin
    $monitor("Time=%0t | RST=%b | J=%b K=%b | Q=%b", $time, rst, j, k, q);
    rst = 1; j = 0; k = 0;
    #10 rst = 0;
    #10 j = 0; k = 0; // Hold
    #10 j = 0; k = 1; // Reset
    #10 j = 1; k = 0; // Set
    #10 j = 1; k = 1; // Toggle
    #10 j = 1; k = 1; // Toggle again
    #10 j = 0; k = 1; // Reset
    #10 j = 1; k = 0; // Set
    #20 $finish;
  end
endmodule

week 6/jkflipflop/jk_ff.vcd
$date
	Mon Sep 08 14:55:14 2025
$end
$version
	Icarus Verilog
$end
$timescale
	1ps
$end
$scope module tb_jk_ff $end
$var wire 1 ! q $end
$var reg 1 " clk $end
$var reg 1 # j $end
$var reg 1 $ k $end
$var reg 1 % rst $end
$scope module jk1 $end
$var wire 1 & clk $end
$var wire 1 ' j $end
$var wire 1 ( k $end
$var wire 1 ) rst $end
$var reg 1 * q $end
$upscope $end
$upscope $end
$enddefinitions $end
#0
$dumpvars
0*
1)
0(
0'
0&
1%
0$
0#
0"
0!
$end
#5000
1"
1&
#10000
0"
0&
0%
0)
#15000
1"
1&
#20000
0"
0&
#25000
1"
1&
#30000
0"
0&
1$
1(
#35000
1"
1&
#40000
0"
0&
0$
0(
1#
1'
#45000
1*
1!
1"
1&
#50000
0"
0&
1$
1(
#55000
0*
0!
1"
1&
#60000
0"
0&
#65000
1*
1!
1"
1&
#70000
0"
0&
0#
0'
#75000
0*
0!
1"
1&
#80000
0"
0&
0$
0(
1#
1'
#85000
1*
1!
1"
1&
