week 6/srflipflop/srflipflop.v
module sr_ff (input wire S, input wire R, input wire clk, input wire rst, output reg Q);
always @(posedge clk)
begin
  if (rst)
    Q <= 1'b0;
  else begin
    case ({S,R})
      2'b00: Q <= Q;        // hold
      2'b01: Q <= 1'b0;     // reset
      2'b10: Q <= 1'b1;     // set
      2'b11: Q <= 1'bx;     // invalid
    endcase
  end
end
endmodule

week 6/srflipflop/srflipflop_tb.v
module TB_SR;
reg S;
reg R;
reg CLK;
reg RST;
wire Q;
sr_ff newSR (.S(S), .R(R), .clk(CLK), .rst(RST), .Q(Q));
initial begin
  CLK=1'b0;
  forever #5 CLK=~CLK;
end
initial begin
  $dumpfile("sr_ff.vcd");
  $dumpvars(0, TB_SR);
end
initial begin
  $monitor("Time=%0t | RST=%b | S=%b R=%b | Q=%b", $time, RST, S, R, Q);
end
initial begin
  RST=1'b1; S=1'b0; R=1'b0; #8;
  RST=1'b0; #6;
  S=1'b0; R=1'b0; #15;  // hold
  S=1'b1; R=1'b0; #10;  // set
  S=1'b0; R=1'b0; #10;  // hold
  S=1'b0; R=1'b1; #10;  // reset
  S=1'b0; R=1'b0; #10;  // hold
  S=1'b1; R=1'b0; #10;  // set
  S=1'b1; R=1'b1; #10;  // invalid
  S=1'b0; R=1'b0; #15;  // hold
  $finish;
end
endmodule

week 6/srflipflop/sr_ff.vcd
$date
	Mon Sep 08 14:49:00 2025
$end
$version
	Icarus Verilog
$end
$timescale
	1s
$end
$scope module TB_SR $end
$var wire 1 ! Q $end
$var reg 1 " CLK $end
$var reg 1 # R $end
$var reg 1 $ RST $end
$var reg 1 % S $end
$scope module newSR $end
$var wire 1 & R $end
$var wire 1 ' S $end
$var wire 1 ( clk $end
$var wire 1 ) rst $end
$var reg 1 * Q $end
$upscope $end
$upscope $end
$enddefinitions $end
#0
$dumpvars
x*
1)
0(
0'
0&
0%
1$
0#
0"
x!
$end
#5
0*
0!
1"
1(
#8
0$
0)
#10
0"
0(
#15
1"
1(
#20
0"
0(
#25
1"
1(
#29
1%
1'
#30
0"
0(
#35
1*
1!
1"
1(
#39
0%
0'
#40
0"
0(
#45
1"
1(
#49
1#
1&
#50
0"
0(
#55
0*
0!
1"
1(
#59
0#
0&
#60
0"
0(
#65
1"
1(
#69
1%
1'
#70
0"
0(
#75
1*
1!
1"
1(
#79
1#
1&
#80
0"
0(
#85
x*
x!
1"
1(
#89
0#
0&
0%
0'
