week 6/-ve edge/Dflipflop.v
module d_ff (input wire D, input wire clk, input wire rst, output reg Q);
  always @(negedge clk) 
begin  
  if (rst)      Q <= 1'b0;     // Asynchronous reset to 0   
 else      Q <= D;        // Sample D on falling edge of clock
  end
endmodule

week 7/Dflipflop_tb.v
`timescale 1ns/1ps

module TB_D;
  reg D;
  reg CLK;
  reg RST;
  wire Q;
  d_ff newD (.D(D), .clk(CLK), .rst(RST), .Q(Q));
  initial begin
    CLK = 1'b0;
    forever #5 CLK = ~CLK;
  end
  initial begin
    $dumpfile("d_ff.vcd");
    $dumpvars(0, TB_D);
  end
  initial begin
    RST = 1'b1;
    D   = 1'b0; #9;
    RST = 1'b0; #6;
    D   = 1'b1; #7;
    D   = 1'b0; #9;
    D   = 1'b1; #11;
    D   = 1'b0; #6;
    RST = 1'b1; #5;
    RST = 1'b0; #15;
    $finish;
  end

initial begin
    $monitor("At time %t, D = %b, RST = %b, Q = %b",$time,D,RST,Q);
  end
endmodule

week 6/Dflipflop/d_ff.vcd
$date
	Mon Sep 08 14:38:47 2025
$end
$version
	Icarus Verilog
$end
$timescale
	1ps
$end
$scope module TB_D $end
$var wire 1 ! Q $end
$var reg 1 " CLK $end
$var reg 1 # D $end
$var reg 1 $ RST $end
$scope module newD $end
$var wire 1 % D $end
$var wire 1 & clk $end
$var wire 1 ' rst $end
$var reg 1 ( Q $end
$upscope $end
$upscope $end
$enddefinitions $end
#0
$dumpvars
x(
1'
0&
0%
1$
0#
0"
x!
$end
#5000
0(
0!
1"
1&
#9000
0$
0'
#10000
0"
0&
#15000
1(
1!
1"
1&
1#
1%
#20000
0"
0&
#22000
0#
0%
#25000
0(
0!
1"
1&
#30000
0"
0&
#31000
1#
1%
#35000
1(
1!
1"
1&
#40000
0"
0&
#42000
0#
0%
#45000
0(
0!
1"
1&
#48000
1$
1'
#50000
0"
0&
#53000
0$
0'
